{"stat.walkOneCm":26185,"stat.mineBlock.minecraft.cactus":2,"stat.leaveGame":1,"stat.damageTaken":180,"stat.mineBlock.minecraft.deadbush":2,"stat.mobKills":5,"stat.useItem.minecraft.rotten_flesh":4,"stat.flyOneCm":169319,"stat.useItem.minecraft.sand":2,"stat.mineBlock.minecraft.sand":2,"stat.jump":168,"stat.swimOneCm":3339,"stat.playOneMinute":5822,"stat.fallOneCm":9413,"stat.killEntity.Villager":1,"stat.damageDealt":750,"stat.crouchOneCm":211,"stat.killEntity.Zombie":1,"stat.timeSinceDeath":5822,"stat.killEntity.Squid":1,"stat.sprintOneCm":12846,"achievement.exploreAllBiomes":{"value":0,"progress":["Beach","DesertHills","Ocean","River","Desert"]},"stat.useItem.minecraft.cactus":2,"stat.diveOneCm":10116}